polyswarm/__init__.py
polyswarm/__main__.py
polyswarm/exceptions.py
polyswarm/polyswarm.py
polyswarm/utils.py
polyswarm/client/__init__.py
polyswarm/client/account.py
polyswarm/client/bundle.py
polyswarm/client/download.py
polyswarm/client/engine.py
polyswarm/client/event.py
polyswarm/client/families.py
polyswarm/client/historical.py
polyswarm/client/links.py
polyswarm/client/live.py
polyswarm/client/metadata.py
polyswarm/client/polyswarm.py
polyswarm/client/report.py
polyswarm/client/report_template.py
polyswarm/client/rules.py
polyswarm/client/sandbox.py
polyswarm/client/scan.py
polyswarm/client/search.py
polyswarm/client/tags.py
polyswarm/client/utils.py
polyswarm/formatters/__init__.py
polyswarm/formatters/base.py
polyswarm/formatters/hashes.py
polyswarm/formatters/json.py
polyswarm/formatters/text.py
polyswarm-3.13.0.dist-info/licenses/LICENSE
polyswarm-3.13.0.dist-info/METADATA
polyswarm-3.13.0.dist-info/WHEEL
polyswarm-3.13.0.dist-info/entry_points.txt
polyswarm-3.13.0.dist-info/top_level.txt
polyswarm-3.13.0.dist-info/RECORD
