Metadata-Version: 2.4
Name: polyswarm
Version: 3.13.0
Summary: CLI for using the PolySwarm Customer APIs
Author-email: PolySwarm Developers <info@polyswarm.io>
License: MIT
Project-URL: Homepage, https://github.com/polyswarm/polyswarm-cli
Classifier: Intended Audience :: Developers
Classifier: License :: OSI Approved :: MIT License
Classifier: Operating System :: OS Independent
Classifier: Programming Language :: Python :: 3.10
Classifier: Programming Language :: Python :: 3.11
Classifier: Programming Language :: Python :: 3.12
Requires-Python: <4,>=3.10
License-File: LICENSE
Requires-Dist: polyswarm_api>=3.13
Requires-Dist: click>=7.1
Requires-Dist: colorama>=0.4.6
Requires-Dist: click-log>=0.4.0
Requires-Dist: pygments>=2.17.2
Provides-Extra: tests
Requires-Dist: bump-my-version~=1.2; extra == "tests"
Requires-Dist: pytest~=8.4; extra == "tests"
Requires-Dist: pytest-cov~=6.2; extra == "tests"
Requires-Dist: PyYAML~=6.0; extra == "tests"
Requires-Dist: vcrpy~=7.0; extra == "tests"
Dynamic: license-file
